{
  "stop_state": "fac64e1918f98c183d06eaacbd45fd25", 
  "event_str": "TouchEvent(state=aded34949cc26d709c2aa8b448066c64, view=753297f2753d27ac306791e93b801f33)", 
  "tag": "2020-03-04_192443", 
  "event": {
    "y": null, 
    "x": null, 
    "event_type": "touch", 
    "view": {
      "content_description": null, 
      "resource_id": null, 
      "text": "\"I believe, ma'am, I may safely promise you never to dance with him.\"", 
      "visible": true, 
      "checkable": false, 
      "children": [], 
      "size": "2*236", 
      "checked": false, 
      "temp_id": 71, 
      "selected": false, 
      "child_count": 0, 
      "content_free_signature": "[class]android.view.View[resource_id]None", 
      "is_password": false, 
      "parent": 32, 
      "focusable": false, 
      "editable": false, 
      "focused": false, 
      "clickable": false, 
      "class": "android.view.View", 
      "scrollable": false, 
      "package": "com.ironServices.audioBooks", 
      "long_clickable": false, 
      "view_str": "753297f2753d27ac306791e93b801f33", 
      "enabled": true, 
      "bounds": [
        [
          1021, 
          929
        ], 
        [
          1023, 
          1165
        ]
      ], 
      "signature": "[class]android.view.View[resource_id]None[text]None[enabled,,]"
    }
  }, 
  "start_state": "aded34949cc26d709c2aa8b448066c64"
}